hyperfunc/__init__.py
hyperfunc/cli/__init__.py
hyperfunc/cli/consumer.py
hyperfunc/config/__init__.py
hyperfunc/config/loader.py
hyperfunc/core/__init__.py
hyperfunc/core/cache.py
hyperfunc/core/decorators.py
hyperfunc/core/mq.py
hyperfunc/core/tests.py
hyperfunc/utils/__init__.py
hyperfunc/utils/exceptions.py
hyperfunc/utils/logger.py
hyperfunc/utils/tests.py
hyperfunc-0.1.2.dist-info/LICENSE
hyperfunc-0.1.2.dist-info/METADATA
hyperfunc-0.1.2.dist-info/WHEEL
hyperfunc-0.1.2.dist-info/entry_points.txt
hyperfunc-0.1.2.dist-info/RECORD
