Metadata-Version: 2.1
Name: hyperfunc
Version: 0.1.2
Summary: 
Author: 0xgustavo
Author-email: 0xgustavo@proton.me
Requires-Python: >=3.9,<4.0
Classifier: Programming Language :: Python :: 3
Classifier: Programming Language :: Python :: 3.9
Classifier: Programming Language :: Python :: 3.10
Classifier: Programming Language :: Python :: 3.11
Classifier: Programming Language :: Python :: 3.12
Requires-Dist: redis (>=5.0.1,<6.0.0)
Requires-Dist: tomli (>=2.0.1,<3.0.0)
